assetic_mapinfo/__init__.py
assetic_mapinfo/__version__.py
assetic_mapinfo/initialise.py
assetic_mapinfo/open_tab_file.py
assetic_mapinfo/simple_test.py
assetic_mapinfo/addin_util/__init__.py
assetic_mapinfo/addin_util/mi_addin_layout_customframe_util.py
assetic_mapinfo/addin_util/mi_addin_resourceManager.py
assetic_mapinfo/addin_util/mi_addin_util.py
assetic_mapinfo/addin_util/mi_common_util.py
assetic_mapinfo/addin_util/mi_user_interaction.py
assetic_mapinfo/settings/__init__.py
assetic_mapinfo/tools/__init__.py
assetic_mapinfo/tools/field_calculations.py
assetic_mapinfo/tools/mapinfo_config.py
assetic_mapinfo/tools/mapinfo_layertools.py
assetic_mapinfo/tools/mapinfo_messager.py
assetic_mapinfo-1.3.0.1.dist-info/LICENSE.txt
assetic_mapinfo-1.3.0.1.dist-info/METADATA
assetic_mapinfo-1.3.0.1.dist-info/WHEEL
assetic_mapinfo-1.3.0.1.dist-info/top_level.txt
assetic_mapinfo-1.3.0.1.dist-info/RECORD
