Metadata-Version: 2.1
Name: assetic-mapinfo
Version: 1.3.0.1
Summary: Assetic MapInfo Integration API
Home-page: http://www.assetic.com
Author-email: developer@assetic.com
Keywords: Assetic MapInfo Integration APIs
License-File: LICENSE.txt
Requires-Dist: assetic (>=2023.16.1.3)
Requires-Dist: pandas (>=0.12.0)
Requires-Dist: six
Requires-Dist: typing
